yamlschema/__init__.py
arrdem.yamlschema-0.1.0.dist-info/METADATA
arrdem.yamlschema-0.1.0.dist-info/WHEEL
arrdem.yamlschema-0.1.0.dist-info/top_level.txt
arrdem.yamlschema-0.1.0.dist-info/RECORD
