Metadata-Version: 2.1
Name: arrdem.yamlschema
Version: 0.1.0
Summary: Detailed JSON schema validation for YAML
Home-page: https://github.com/arrdem/source
Author: Reid 'arrdem' McKenzie
Author-email: me@arrdem.com
License: MIT
Platform: UNKNOWN
Classifier: License :: OSI Approved :: MIT License
Classifier: Development Status :: 3 - Alpha
Classifier: Intended Audience :: Developers
Classifier: Programming Language :: Python :: 3
Classifier: Programming Language :: Python :: 3.8
Requires-Dist: PyYAML (~=5.4.1)
